README.md
setup.py
Telezhka/__init__.py
Telezhka/telezhka.py
Telezhka.egg-info/PKG-INFO
Telezhka.egg-info/SOURCES.txt
Telezhka.egg-info/dependency_links.txt
Telezhka.egg-info/requires.txt
Telezhka.egg-info/top_level.txt