Metadata-Version: 2.1
Name: Telezhka
Version: 0.0.2
Summary: Telegram api library in python
Home-page: https://github.com/dmitrijkotov634/Telezhka
Author: dmitrijkotov
Author-email: dmitrijkotov634@mail.ru
License: MIT
Keywords: Telegram
Platform: UNKNOWN
Classifier: Programming Language :: Python :: 3
Classifier: Programming Language :: Python :: 3.4
Classifier: Programming Language :: Python :: 3.5
Classifier: Programming Language :: Python :: 3.6
Classifier: Programming Language :: Python :: 3.7
Classifier: License :: OSI Approved :: MIT License
Classifier: Operating System :: OS Independent
Requires-Python: >=3
